yalidine/__init__.py
yalidine/api.py
yalidine/entity.py
yalidine/settings.py
yalidine-0.0.3.dist-info/LICENSE
yalidine-0.0.3.dist-info/METADATA
yalidine-0.0.3.dist-info/WHEEL
yalidine-0.0.3.dist-info/top_level.txt
yalidine-0.0.3.dist-info/RECORD
