Metadata-Version: 2.1
Name: yalidine
Version: 0.0.3
Summary: This package is to integrate Yalidine api easily.
Author-email: Berkane Tarek <tarekg320@gmail.com>
License: MIT
Keywords: yalidine,livraison,delivery
Classifier: Programming Language :: Python :: 3
Requires-Python: >=3.7
License-File: LICENSE
Requires-Dist: requests ==2.31
